{"users":{"223157271973199873":{"aliases":["dmoosey"],"permissions":{},"pool":{"fizz":{"viktor":{"winrate":"51.71","sample":"13625"},"yone":{"winrate":"52.46","sample":"22419"},"syndra":{"winrate":"57.78","sample":"5064"}},"ekko":{"viktor":{"winrate":"52.16","sample":"14416"},"yone":{"winrate":"51.88","sample":"17188"},"syndra":{"winrate":"57.41","sample":"4245"}},"zoe":{"viktor":{"winrate":"47.81","sample":"7318"},"yone":{"winrate":"47.99","sample":"10068"},"syndra":{"winrate":"51.16","sample":"3057"}}}},"284376423404404737":{"aliases":["frankie"],"permissions":{},"pool":{"miss fortune":{},"kai'sa":{},"jhin":{}}}}}